MANIFEST.in
setup.py
py_shelf.egg-info/PKG-INFO
py_shelf.egg-info/SOURCES.txt
py_shelf.egg-info/dependency_links.txt
py_shelf.egg-info/requires.txt
py_shelf.egg-info/top_level.txt
shelf/__init__.py
shelf/__main__.py
shelf/__version__.py
shelf/relocate.py
shelf/api/__init__.py
shelf/api/api.py
shelf/api/utilities/__init__.py
shelf/api/utilities/binary.py
shelf/arm/__init__.py
shelf/arm/aarch64_dynamic_relocations.py
shelf/arm/arm_32_dynamic_relocations.py
shelf/arm/x32.py
shelf/arm/x64.py
shelf/hooks/__init__.py
shelf/hooks/base_hook.py
shelf/hooks/hooks_configuration_parser.py
shelf/hooks/builtin/__init__.py
shelf/hooks/builtin/change_memory_protection.py
shelf/hooks/builtin/descriptors.py
shelf/hooks/builtin/rwx_bypass.py
shelf/intel/__init__.py
shelf/intel/intel_irelative_relocations.py
shelf/intel/x32.py
shelf/intel/x32_dynamic_relocations.py
shelf/intel/x32_opcodes_analysis.py
shelf/intel/x64.py
shelf/intel/x64_dynamic_relocations.py
shelf/lib/__init__.py
shelf/lib/consts.py
shelf/lib/exceptions.py
shelf/lib/five.py
shelf/lib/shellcode.py
shelf/lib/ext/__init__.py
shelf/lib/ext/dynamic_relocations_base.py
shelf/lib/ext/loader_symbols.py
shelf/lib/ext/opcodes_analysis_base.py
shelf/lib/plugins/__init__.py
shelf/lib/plugins/base_shelf_plugins.py
shelf/lib/plugins/memory_dump/__init__.py
shelf/lib/plugins/memory_dump/shelf_memory_dumps_plugin.py
shelf/lib/utils/__init__.py
shelf/lib/utils/address_utils.py
shelf/lib/utils/disassembler.py
shelf/lib/utils/general.py
shelf/lib/utils/hooks.py
shelf/lib/utils/match_utils.py
shelf/lib/utils/memory_section.py
shelf/lib/utils/mini_loader.py
shelf/lib/utils/objdump_disassembler_backend.py
shelf/lib/utils/process.py
shelf/mips/__init__.py
shelf/mips/mips.py
shelf/mips/mips_dynamic_relocations.py
shelf/resources/__init__.py
shelf/resources/mini_loader_arm_x32.shellcode
shelf/resources/mini_loader_arm_x32.shellcode.relative.symbols
shelf/resources/mini_loader_arm_x32.shellcode.structs.json
shelf/resources/mini_loader_arm_x32.shellcode.symbols
shelf/resources/mini_loader_arm_x32_dynamic.shellcode
shelf/resources/mini_loader_arm_x32_dynamic.shellcode.relative.symbols
