Metadata-Version: 2.1
Name: py-shelf
Version: 3.0.6
Summary: Python package to create shellcodes from elfs supported arch (mips, arm (32bit), i386 32bit, i386 64bit, aarch64, RISC-V rv64 P)
Home-page: https://github.com/jonatanSh/shelf
Author: Jonathan Shimon
Author-email: jonatanshimon@gmail.com
License: MIT License
Platform: UNKNOWN
